numcodecs_wasm_swizzle_reshape/__init__.py
numcodecs_wasm_swizzle_reshape/__init__.pyi
numcodecs_wasm_swizzle_reshape/codec.wasm
numcodecs_wasm_swizzle_reshape/py.typed
numcodecs_wasm_swizzle_reshape-0.4.0.dist-info/METADATA
numcodecs_wasm_swizzle_reshape-0.4.0.dist-info/WHEEL
numcodecs_wasm_swizzle_reshape-0.4.0.dist-info/entry_points.txt
numcodecs_wasm_swizzle_reshape-0.4.0.dist-info/top_level.txt
numcodecs_wasm_swizzle_reshape-0.4.0.dist-info/RECORD
